{
  "last_update": "2026-07-22T17:23:41.071517",
  "users": [
    {
      "name": "宁思禹",
      "grade": "2024 级",
      "handle": "anoslide",
      "rating": 1605,
      "maxRating": 1657,
      "rank": "expert",
      "recentContest": "Educational Codeforces Round 190 (Rated for Div. 2)",
      "ratingChange": -6,
      "solvedCount": 298
    },
    {
      "name": "吴帅甫",
      "grade": "2023 级",
      "handle": "ziyvoo",
      "rating": 1568,
      "maxRating": 1569,
      "rank": "specialist",
      "recentContest": "Codeforces Round 1046 (Div. 2)",
      "ratingChange": 14,
      "solvedCount": 324
    },
    {
      "name": "翟景旺",
      "grade": "2024 级",
      "handle": "Yhh7.",
      "rating": 1567,
      "maxRating": 1737,
      "rank": "specialist",
      "recentContest": "Educational Codeforces Round 191 (Rated for Div. 2)",
      "ratingChange": 38,
      "solvedCount": 418
    },
    {
      "name": "吴静轩",
      "grade": "2024 级",
      "handle": "Tbat",
      "rating": 1519,
      "maxRating": 1522,
      "rank": "specialist",
      "recentContest": "Educational Codeforces Round 191 (Rated for Div. 2)",
      "ratingChange": 45,
      "solvedCount": 485
    },
    {
      "name": "马傲博",
      "grade": "2024 级",
      "handle": "maj_22",
      "rating": 1462,
      "maxRating": 1462,
      "rank": "specialist",
      "recentContest": "Codeforces Round 1102 (Div. 2)",
      "ratingChange": 7,
      "solvedCount": 601
    },
    {
      "name": "李海瑜",
      "grade": "2024 级",
      "handle": "iyu0",
      "rating": 1421,
      "maxRating": 1421,
      "rank": "specialist",
      "recentContest": "Codeforces Round 1103 (Div. 3)",
      "ratingChange": 22,
      "solvedCount": 822
    },
    {
      "name": "赵柯行",
      "grade": "2024 级",
      "handle": "zhaokx12.",
      "rating": 1411,
      "maxRating": 1411,
      "rank": "specialist",
      "recentContest": "Codeforces Round 1091 (Div. 2) and CodeCraft 26",
      "ratingChange": 60,
      "solvedCount": 312
    },
    {
      "name": "王义博",
      "grade": "2025 级",
      "handle": "wert2353",
      "rating": 1407,
      "maxRating": 1523,
      "rank": "specialist",
      "recentContest": "Educational Codeforces Round 191 (Rated for Div. 2)",
      "ratingChange": -34,
      "solvedCount": 198
    },
    {
      "name": "李昶昊",
      "grade": "2024 级",
      "handle": "_HP",
      "rating": 1384,
      "maxRating": 1509,
      "rank": "pupil",
      "recentContest": "Educational Codeforces Round 191 (Rated for Div. 2)",
      "ratingChange": -104,
      "solvedCount": 340
    },
    {
      "name": "余锦昊",
      "grade": "2024 级",
      "handle": "yokin",
      "rating": 1376,
      "maxRating": 1445,
      "rank": "pupil",
      "recentContest": "Spectral::Cup 2026 Round 1 (Codeforces Round 1094, Div. 1 + Div. 2)",
      "ratingChange": -15,
      "solvedCount": 414
    },
    {
      "name": "强锦铭",
      "grade": "2024 级",
      "handle": "Ayake",
      "rating": 1356,
      "maxRating": 1537,
      "rank": "pupil",
      "recentContest": "Educational Codeforces Round 189 (Rated for Div. 2)",
      "ratingChange": -26,
      "solvedCount": 280
    },
    {
      "name": "李宇恒",
      "grade": "2025 级",
      "handle": "liyyuu",
      "rating": 1302,
      "maxRating": 1366,
      "rank": "pupil",
      "recentContest": "Codeforces Round 1111 (Div. 2)",
      "ratingChange": -28,
      "solvedCount": 381
    },
    {
      "name": "曹继喆",
      "grade": "2024 级",
      "handle": "cola2100",
      "rating": 1289,
      "maxRating": 1410,
      "rank": "pupil",
      "recentContest": "Codeforces Round 1044 (Div. 2)",
      "ratingChange": -36,
      "solvedCount": 406
    },
    {
      "name": "李昊洋",
      "grade": "2024 级",
      "handle": "LHY0715",
      "rating": 1271,
      "maxRating": 1276,
      "rank": "pupil",
      "recentContest": "Codeforces Round 1111 (Div. 2)",
      "ratingChange": 23,
      "solvedCount": 162
    },
    {
      "name": "侯轶棠",
      "grade": "2025 级",
      "handle": "biyuf",
      "rating": 1270,
      "maxRating": 1321,
      "rank": "pupil",
      "recentContest": "Educational Codeforces Round 191 (Rated for Div. 2)",
      "ratingChange": 25,
      "solvedCount": 183
    },
    {
      "name": "申海辰",
      "grade": "2024 级",
      "handle": "monesytop1",
      "rating": 1244,
      "maxRating": 1260,
      "rank": "pupil",
      "recentContest": "Codeforces Round 1099 (Div. 2)",
      "ratingChange": 15,
      "solvedCount": 184
    },
    {
      "name": "段荆玺",
      "grade": "2025 级",
      "handle": "buhuizuo",
      "rating": 1233,
      "maxRating": 1328,
      "rank": "pupil",
      "recentContest": "Codeforces Round 1103 (Div. 3)",
      "ratingChange": 9,
      "solvedCount": 206
    },
    {
      "name": "王巍",
      "grade": "2024 级",
      "handle": "wwac",
      "rating": 1220,
      "maxRating": 1220,
      "rank": "pupil",
      "recentContest": "Educational Codeforces Round 190 (Rated for Div. 2)",
      "ratingChange": 36,
      "solvedCount": 90
    },
    {
      "name": "梁敬泽",
      "grade": "2025 级",
      "handle": "Ljzmlx",
      "rating": 1218,
      "maxRating": 1218,
      "rank": "pupil",
      "recentContest": "Codeforces Round 1103 (Div. 3)",
      "ratingChange": 64,
      "solvedCount": 105
    },
    {
      "name": "李忆恩",
      "grade": "2025 级",
      "handle": "jim_jrodan",
      "rating": 1214,
      "maxRating": 1259,
      "rank": "pupil",
      "recentContest": "Codeforces Round 1102 (Div. 2)",
      "ratingChange": -45,
      "solvedCount": 138
    },
    {
      "name": "周佳影",
      "grade": "2025 级",
      "handle": "XYZz-",
      "rating": 1212,
      "maxRating": 1308,
      "rank": "pupil",
      "recentContest": "Codeforces Round 1099 (Div. 2)",
      "ratingChange": -45,
      "solvedCount": 133
    },
    {
      "name": "张玉桂",
      "grade": "2024 级",
      "handle": "zygnb",
      "rating": 1206,
      "maxRating": 1333,
      "rank": "pupil",
      "recentContest": "Educational Codeforces Round 191 (Rated for Div. 2)",
      "ratingChange": 71,
      "solvedCount": 1040
    },
    {
      "name": "栗晟皓",
      "grade": "2024 级",
      "handle": "lichenghao",
      "rating": 1199,
      "maxRating": 1214,
      "rank": "newbie",
      "recentContest": "Codeforces Round 1095 (Div. 2)",
      "ratingChange": 0,
      "solvedCount": 74
    },
    {
      "name": "孙艺菲",
      "grade": "2025 级",
      "handle": "s1fzzz",
      "rating": 1170,
      "maxRating": 1196,
      "rank": "newbie",
      "recentContest": "Codeforces Round 1102 (Div. 2)",
      "ratingChange": -26,
      "solvedCount": 92
    },
    {
      "name": "貌克宇",
      "grade": "2025 级",
      "handle": "mky0800",
      "rating": 1157,
      "maxRating": 1157,
      "rank": "newbie",
      "recentContest": "Educational Codeforces Round 189 (Rated for Div. 2)",
      "ratingChange": 82,
      "solvedCount": 58
    },
    {
      "name": "单鑫亮",
      "grade": "2024 级",
      "handle": "YellowDragon",
      "rating": 1076,
      "maxRating": 1207,
      "rank": "newbie",
      "recentContest": "Codeforces Round 1111 (Div. 2)",
      "ratingChange": -19,
      "solvedCount": 44
    },
    {
      "name": "石熙琛",
      "grade": "2025 级",
      "handle": "ttwansuiye",
      "rating": 1069,
      "maxRating": 1102,
      "rank": "newbie",
      "recentContest": "Codeforces Round 1096 (Div. 3)",
      "ratingChange": -33,
      "solvedCount": 61
    },
    {
      "name": "靳宇翔",
      "grade": "2025 级",
      "handle": "changf",
      "rating": 1029,
      "maxRating": 1043,
      "rank": "newbie",
      "recentContest": "Educational Codeforces Round 190 (Rated for Div. 2)",
      "ratingChange": -14,
      "solvedCount": 34
    },
    {
      "name": "李昆鹏",
      "grade": "2025 级",
      "handle": "likunpeng",
      "rating": 1019,
      "maxRating": 1061,
      "rank": "newbie",
      "recentContest": "Educational Codeforces Round 190 (Rated for Div. 2)",
      "ratingChange": 105,
      "solvedCount": 46
    },
    {
      "name": "安齐镭",
      "grade": "2025 级",
      "handle": "ANQILEI",
      "rating": 1016,
      "maxRating": 1103,
      "rank": "newbie",
      "recentContest": "Codeforces Round 1102 (Div. 2)",
      "ratingChange": -87,
      "solvedCount": 79
    },
    {
      "name": "解天蔚",
      "grade": "2025 级",
      "handle": "xtwaaa",
      "rating": 1006,
      "maxRating": 1018,
      "rank": "newbie",
      "recentContest": "Codeforces Round 1102 (Div. 2)",
      "ratingChange": -9,
      "solvedCount": 101
    },
    {
      "name": "郑于威",
      "grade": "2023 级",
      "handle": "zhengxiaomei",
      "rating": 956,
      "maxRating": 1112,
      "rank": "newbie",
      "recentContest": "Codeforces Round 1098 (Div. 2)",
      "ratingChange": 30,
      "solvedCount": 106
    },
    {
      "name": "王思哲",
      "grade": "2025 级",
      "handle": "warning......",
      "rating": 936,
      "maxRating": 1010,
      "rank": "newbie",
      "recentContest": "Codeforces Round 1098 (Div. 2)",
      "ratingChange": 23,
      "solvedCount": 48
    },
    {
      "name": "秦旭阳",
      "grade": "2025 级",
      "handle": "oldust520",
      "rating": 936,
      "maxRating": 996,
      "rank": "newbie",
      "recentContest": "Codeforces Round 1077 (Div. 2)",
      "ratingChange": -60,
      "solvedCount": 8
    },
    {
      "name": "刘敬泽",
      "grade": "2025 级",
      "handle": "anyidemao",
      "rating": 931,
      "maxRating": 973,
      "rank": "newbie",
      "recentContest": "Codeforces Round 1102 (Div. 2)",
      "ratingChange": 39,
      "solvedCount": 36
    },
    {
      "name": "朱宏璟",
      "grade": "2025 级",
      "handle": "xing_he",
      "rating": 927,
      "maxRating": 927,
      "rank": "newbie",
      "recentContest": "Codeforces Round 1091 (Div. 2) and CodeCraft 26",
      "ratingChange": 70,
      "solvedCount": 16
    },
    {
      "name": "赵庆淇",
      "grade": "2025 级",
      "handle": "nanhaijuzi",
      "rating": 864,
      "maxRating": 996,
      "rank": "newbie",
      "recentContest": "Educational Codeforces Round 189 (Rated for Div. 2)",
      "ratingChange": -38,
      "solvedCount": 16
    },
    {
      "name": "李领玉",
      "grade": "2025 级",
      "handle": "lilingyu..",
      "rating": 858,
      "maxRating": 977,
      "rank": "newbie",
      "recentContest": "Educational Codeforces Round 191 (Rated for Div. 2)",
      "ratingChange": 36,
      "solvedCount": 38
    },
    {
      "name": "张正正",
      "grade": "2024 级",
      "handle": "zhangzhengzheng",
      "rating": 852,
      "maxRating": 951,
      "rank": "newbie",
      "recentContest": "Codeforces Round 1093 (Div. 2)",
      "ratingChange": -2,
      "solvedCount": 33
    },
    {
      "name": "刘晓玲",
      "grade": "2023 级",
      "handle": "Cutee",
      "rating": 836,
      "maxRating": 906,
      "rank": "newbie",
      "recentContest": "Codeforces Round 1093 (Div. 2)",
      "ratingChange": 26,
      "solvedCount": 19
    },
    {
      "name": "乔泉程",
      "grade": "2025 级",
      "handle": "discovery...",
      "rating": 821,
      "maxRating": 1073,
      "rank": "newbie",
      "recentContest": "Educational Codeforces Round 190 (Rated for Div. 2)",
      "ratingChange": -9,
      "solvedCount": 51
    },
    {
      "name": "王金燕",
      "grade": "2025 级",
      "handle": "w19511030691",
      "rating": 814,
      "maxRating": 878,
      "rank": "newbie",
      "recentContest": "Spectral::Cup 2026 Round 1 (Codeforces Round 1094, Div. 1 + Div. 2)",
      "ratingChange": 40,
      "solvedCount": 21
    },
    {
      "name": "张稳泉",
      "grade": "2025 级",
      "handle": "zwq123180",
      "rating": 811,
      "maxRating": 883,
      "rank": "newbie",
      "recentContest": "Codeforces Round 1096 (Div. 3)",
      "ratingChange": 66,
      "solvedCount": 42
    },
    {
      "name": "高耀",
      "grade": "2025 级",
      "handle": "DAIPUTAO",
      "rating": 804,
      "maxRating": 956,
      "rank": "newbie",
      "recentContest": "Codeforces Round 1095 (Div. 2)",
      "ratingChange": 70,
      "solvedCount": 26
    }
  ]
}